itf_py/__init__.py
itf_py/itf.py
itf_py-0.4.3.dist-info/METADATA
itf_py-0.4.3.dist-info/WHEEL
itf_py-0.4.3.dist-info/RECORD
