Metadata-Version: 2.4
Name: itf-py
Version: 0.4.3
Summary: Python library to parse and emit Apalache/Quint traces in ITF JSON
Keywords: itf,trace,parser,tlaplus,apalache,quint
Author: Igor Konnov
Author-email: igor@konnov.phd
Requires-Python: >=3.12,<4.0
Classifier: Programming Language :: Python :: 3
Classifier: Programming Language :: Python :: 3.12
Classifier: Programming Language :: Python :: 3.13
Classifier: Programming Language :: Python :: 3.14
Requires-Dist: frozendict (>=2.4.6,<3.0.0)
Project-URL: Homepage, https://github.com/konnov/itf-py
